setup.py
tc_mongodb/__init__.py
tc_mongodb.egg-info/PKG-INFO
tc_mongodb.egg-info/SOURCES.txt
tc_mongodb.egg-info/dependency_links.txt
tc_mongodb.egg-info/requires.txt
tc_mongodb.egg-info/top_level.txt
tc_mongodb/result_storages/__init__.py
tc_mongodb/storages/__init__.py
tc_mongodb/storages/mongo_storage.py