Metadata-Version: 1.1
Name: tc-mongodb
Version: 5.1.0
Summary: Thumbor thumbor storage adapters
Home-page: https://github.com/thumbor-community/mongodb
Author: Thumbor Community
Author-email: UNKNOWN
License: MIT
Keywords: thumbor mongodb mongo
Platform: UNKNOWN
Classifier: Development Status :: 5 - Production/Stable
Classifier: License :: OSI Approved :: MIT License
Classifier: Programming Language :: Python :: 2.7
